fastoad_cs25/__init__.py
fastoad_cs25/configurations/__init__.py
fastoad_cs25/configurations/cs25_base.yaml
fastoad_cs25/models/__init__.py
fastoad_cs25/models/aerodynamics/__init__.py
fastoad_cs25/models/aerodynamics/aerodynamics_high_speed.py
fastoad_cs25/models/aerodynamics/aerodynamics_landing.py
fastoad_cs25/models/aerodynamics/aerodynamics_low_speed.py
fastoad_cs25/models/aerodynamics/aerodynamics_takeoff.py
fastoad_cs25/models/aerodynamics/components/__init__.py
fastoad_cs25/models/aerodynamics/components/cd0.py
fastoad_cs25/models/aerodynamics/components/cd0_fuselage.py
fastoad_cs25/models/aerodynamics/components/cd0_ht.py
fastoad_cs25/models/aerodynamics/components/cd0_nacelles_pylons.py
fastoad_cs25/models/aerodynamics/components/cd0_total.py
fastoad_cs25/models/aerodynamics/components/cd0_vt.py
fastoad_cs25/models/aerodynamics/components/cd0_wing.py
fastoad_cs25/models/aerodynamics/components/cd_compressibility.py
fastoad_cs25/models/aerodynamics/components/cd_trim.py
fastoad_cs25/models/aerodynamics/components/compute_alpha.py
fastoad_cs25/models/aerodynamics/components/compute_cl_alpha.py
fastoad_cs25/models/aerodynamics/components/compute_max_cl_landing.py
fastoad_cs25/models/aerodynamics/components/compute_polar.py
fastoad_cs25/models/aerodynamics/components/compute_reynolds.py
fastoad_cs25/models/aerodynamics/components/high_lift_aero.py
fastoad_cs25/models/aerodynamics/components/initialize_cl.py
fastoad_cs25/models/aerodynamics/components/oswald.py
fastoad_cs25/models/aerodynamics/components/resources/__init__.py
fastoad_cs25/models/aerodynamics/components/resources/interpolation of lift effectiveness.txt
fastoad_cs25/models/aerodynamics/components/utils/__init__.py
fastoad_cs25/models/aerodynamics/components/utils/cd0_lifting_surface.py
fastoad_cs25/models/aerodynamics/components/utils/friction_drag.py
fastoad_cs25/models/aerodynamics/constants.py
fastoad_cs25/models/aerodynamics/external/__init__.py
fast_oad_cs25-0.8.0.dist-info/AUTHORS.rst
fast_oad_cs25-0.8.0.dist-info/LICENSE
fast_oad_cs25-0.8.0.dist-info/METADATA
fast_oad_cs25-0.8.0.dist-info/WHEEL
fast_oad_cs25-0.8.0.dist-info/entry_points.txt
fast_oad_cs25-0.8.0.dist-info/RECORD
