Metadata-Version: 2.1
Name: FAST-OAD-CS25
Version: 0.8.0
Summary: FAST-OAD_CS25 is a FAST-OAD plugin with CS25/FAR25-related models.
Home-page: https://github.com/fast-aircraft-design/FAST-OAD_CS25
License: GPL-3.0-only
Keywords: aircraft,design,multi-disciplinary
Author: Christophe DAVID
Author-email: christophe.david@onera.fr
Requires-Python: >=3.9,<4.0
Classifier: Development Status :: 4 - Beta
Classifier: Environment :: Console
Classifier: Intended Audience :: Education
Classifier: Intended Audience :: Science/Research
Classifier: License :: OSI Approved :: GNU General Public License v3 (GPLv3)
Classifier: Natural Language :: English
Classifier: Operating System :: MacOS
Classifier: Operating System :: Microsoft :: Windows
Classifier: Operating System :: POSIX :: Linux
Classifier: Programming Language :: Python :: 3
Classifier: Programming Language :: Python :: 3.9
Classifier: Programming Language :: Python :: 3.10
Classifier: Programming Language :: Python :: 3.11
Classifier: Programming Language :: Python :: 3.12
Classifier: Topic :: Scientific/Engineering :: Physics
Requires-Dist: fast-oad-core (>=1.8.4,<2.0.0) ; python_version < "3.13"
Requires-Dist: pyparsing (>=3.0.0,<4.0.0)
